moviepy/Clip.py
moviepy/__init__.py
moviepy/compat.py
moviepy/config.py
moviepy/config_defaults.py
moviepy/decorators.py
moviepy/editor.py
moviepy/tools.py
moviepy/utils.py
moviepy/version.py
moviepy/audio/AudioClip.py
moviepy/audio/__init__.py
moviepy/audio/fx/__init__.py
moviepy/audio/fx/audio_fadein.py
moviepy/audio/fx/audio_fadeout.py
moviepy/audio/fx/audio_left_right.py
moviepy/audio/fx/audio_loop.py
moviepy/audio/fx/audio_normalize.py
moviepy/audio/fx/volumex.py
moviepy/audio/fx/all/__init__.py
moviepy/audio/io/AudioFileClip.py
moviepy/audio/io/__init__.py
moviepy/audio/io/ffmpeg_audiowriter.py
moviepy/audio/io/preview.py
moviepy/audio/io/readers.py
moviepy/audio/tools/__init__.py
moviepy/audio/tools/cuts.py
moviepy/video/VideoClip.py
moviepy/video/__init__.py
moviepy/video/compositing/CompositeVideoClip.py
moviepy/video/compositing/__init__.py
moviepy/video/compositing/concatenate.py
moviepy/video/compositing/on_color.py
moviepy/video/compositing/positioning.py
moviepy/video/compositing/transitions.py
moviepy/video/fx/__init__.py
moviepy/video/fx/accel_decel.py
moviepy/video/fx/blackwhite.py
moviepy/video/fx/blink.py
moviepy/video/fx/colorx.py
moviepy/video/fx/crop.py
moviepy/video/fx/even_size.py
moviepy/video/fx/fadein.py
moviepy/video/fx/fadeout.py
moviepy/video/fx/freeze.py
moviepy/video/fx/freeze_region.py
moviepy/video/fx/gamma_corr.py
moviepy/video/fx/headblur.py
moviepy/video/fx/invert_colors.py
moviepy/video/fx/loop.py
moviepy/video/fx/lum_contrast.py
moviepy/video/fx/make_loopable.py
moviepy/video/fx/margin.py
moviepy/video/fx/mask_and.py
moviepy/video/fx/mask_color.py
moviepy/video/fx/mask_or.py
moviepy/video/fx/mirror_x.py
moviepy/video/fx/mirror_y.py
moviepy/video/fx/painting.py
moviepy/video/fx/resize.py
moviepy/video/fx/rotate.py
moviepy/video/fx/scroll.py
moviepy/video/fx/speedx.py
moviepy/video/fx/supersample.py
moviepy/video/fx/time_mirror.py
moviepy/video/fx/time_symmetrize.py
moviepy/video/fx/all/__init__.py
moviepy_bg-1.0.5.dist-info/LICENCE.txt
moviepy_bg-1.0.5.dist-info/METADATA
moviepy_bg-1.0.5.dist-info/WHEEL
moviepy_bg-1.0.5.dist-info/top_level.txt
moviepy_bg-1.0.5.dist-info/RECORD
